piq/__init__.py
piq/base.py
piq/brisque.py
piq/clip_iqa.py
piq/dss.py
piq/fid.py
piq/fsim.py
piq/gmsd.py
piq/gs.py
piq/haarpsi.py
piq/isc.py
piq/iw_ssim.py
piq/kid.py
piq/mdsi.py
piq/ms_ssim.py
piq/msid.py
piq/perceptual.py
piq/pieapp.py
piq/pr.py
piq/psnr.py
piq/srsim.py
piq/ssim.py
piq/tv.py
piq/vif.py
piq/vsi.py
piq/feature_extractors/__init__.py
piq/feature_extractors/clip.py
piq/feature_extractors/fid_inception.py
piq/functional/__init__.py
piq/functional/base.py
piq/functional/colour_conversion.py
piq/functional/filters.py
piq/functional/layers.py
piq/functional/resize.py
piq/utils/__init__.py
piq/utils/common.py
piq-0.8.0.dist-info/LICENSE
piq-0.8.0.dist-info/METADATA
piq-0.8.0.dist-info/WHEEL
piq-0.8.0.dist-info/top_level.txt
piq-0.8.0.dist-info/RECORD
