Metadata-Version: 2.1
Name: piq
Version: 0.8.0
Summary: Measures and metrics for image2image tasks. PyTorch.
Home-page: https://github.com/photosynthesis-team/piq
Author: Sergey Kastryulin
Author-email: snk4tr@gmail.com
Classifier: Programming Language :: Python :: 3
Classifier: License :: OSI Approved :: Apache Software License
Classifier: Operating System :: OS Independent
License-File: LICENSE
Requires-Dist: torchvision (>=0.10.0)
